{
  "id": "openclaw-rest-channel",
  "name": "REST Channel",
  "description": "A minimal REST-based channel plugin for OpenClaw. Connect any external web application via simple HTTP requests.",
  "version": "1.0.0",
  "channels": ["rest"],
  "configSchema": {
    "type": "object",
    "additionalProperties": false,
    "properties": {
      "webhookUrl": {
        "type": "string",
        "description": "URL where OpenClaw sends outbound messages (assistant replies). Your app must accept POST requests at this URL."
      },
      "webhookSecret": {
        "type": "string",
        "description": "Shared secret for signing outbound webhook payloads (HMAC-SHA256). Set this to verify that requests to your webhook actually come from OpenClaw."
      },
      "apiKey": {
        "type": "string",
        "description": "API key that external clients must include when sending inbound messages to OpenClaw. Acts as bearer token authentication."
      },
      "inboundPath": {
        "type": "string",
        "default": "/rest/inbound",
        "description": "HTTP path on the Gateway where inbound messages are received."
      },
      "allowPrivateNetwork": {
        "type": "boolean",
        "default": false,
        "description": "Allow fetching media attachments from private/internal network addresses (localhost, 192.168.x.x, etc.). Enable this when your app serves attachments from a local URL."
      },
      "mediaMaxMb": {
        "type": "number",
        "default": 8,
        "description": "Maximum size in MB for a single media attachment download. Attachments exceeding this limit are skipped."
      }
    }
  },
  "uiHints": {
    "webhookUrl": {
      "label": "Webhook URL",
      "placeholder": "https://your-app.example.com/openclaw/webhook"
    },
    "webhookSecret": {
      "label": "Webhook Secret",
      "sensitive": true
    },
    "apiKey": {
      "label": "Inbound API Key",
      "sensitive": true
    },
    "inboundPath": {
      "label": "Inbound Path",
      "placeholder": "/rest/inbound"
    },
    "allowPrivateNetwork": {
      "label": "Allow Private Network",
      "description": "Enable if your app serves attachment files from localhost or a private IP"
    },
    "mediaMaxMb": {
      "label": "Media Max Size (MB)",
      "placeholder": "8"
    }
  }
}
